polyfile/__init__.py
polyfile/__main__.py
polyfile/arithmetic.py
polyfile/ast.py
polyfile/debugger.py
polyfile/expressions.py
polyfile/fileutils.py
polyfile/html.py
polyfile/iterators.py
polyfile/jpeg.py
polyfile/kaitaimatcher.py
polyfile/languagematcher.py
polyfile/logger.py
polyfile/magic.py
polyfile/nes.py
polyfile/nitf.py
polyfile/pdf.py
polyfile/pickles.py
polyfile/polyfile.py
polyfile/profiling.py
polyfile/repl.py
polyfile/search.py
polyfile/serialization.py
polyfile/structmatcher.py
polyfile/structs.py
polyfile/wildcards.py
polyfile/zipmatcher.py
polyfile/http/__init__.py
polyfile/http/defacto.py
polyfile/http/deprecated.py
polyfile/http/experimental.py
polyfile/http/http_11.py
polyfile/http/matcher.py
polyfile/http/structured_headers.py
polyfile/kaitai/__init__.py
polyfile/kaitai/compiler.py
polyfile/kaitai/parser.py
polyfile/kaitai/parsers/__init__.py
polyfile/kaitai/parsers/aix_utmp.py
polyfile/kaitai/parsers/allegro_dat.py
polyfile/kaitai/parsers/andes_firmware.py
polyfile/kaitai/parsers/android_bootldr_asus.py
polyfile/kaitai/parsers/android_bootldr_huawei.py
polyfile/kaitai/parsers/android_bootldr_qcom.py
polyfile/kaitai/parsers/android_dto.py
polyfile/kaitai/parsers/android_img.py
polyfile/kaitai/parsers/android_nanoapp_header.py
polyfile/kaitai/parsers/android_opengl_shaders_cache.py
polyfile/kaitai/parsers/android_sparse.py
polyfile/kaitai/parsers/android_super.py
polyfile/kaitai/parsers/apm_partition_table.py
polyfile/kaitai/parsers/apple_single_double.py
polyfile/kaitai/parsers/asn1_der.py
polyfile/kaitai/parsers/au.py
polyfile/kaitai/parsers/avantes_roh60.py
polyfile/kaitai/parsers/avi.py
polyfile/kaitai/parsers/bcd.py
polyfile/kaitai/parsers/bitcoin_transaction.py
polyfile/kaitai/parsers/blender_blend.py
polyfile/kaitai/parsers/bmp.py
polyfile/kaitai/parsers/bson.py
polyfile/kaitai/parsers/btrfs_stream.py
polyfile/kaitai/parsers/bytes_with_io.py
polyfile/kaitai/parsers/chrome_pak.py
polyfile/kaitai/parsers/code_6502.py
polyfile_weave-0.5.8.dist-info/licenses/LICENSE
polyfile_weave-0.5.8.dist-info/METADATA
polyfile_weave-0.5.8.dist-info/WHEEL
polyfile_weave-0.5.8.dist-info/entry_points.txt
polyfile_weave-0.5.8.dist-info/top_level.txt
polyfile_weave-0.5.8.dist-info/RECORD
