Metadata-Version: 2.4
Name: polyfile-weave
Version: 0.5.8
Summary: A utility to recursively map the structure of a file.
Home-page: https://github.com/zbirenbaum/polyfile-weave
Author: Trail of Bits
Classifier: Development Status :: 4 - Beta
Classifier: Environment :: Console
Classifier: Intended Audience :: Science/Research
Classifier: License :: OSI Approved :: Apache Software License
Classifier: Programming Language :: Python :: 3 :: Only
Classifier: Topic :: Security
Classifier: Topic :: Software Development :: Testing
Classifier: Topic :: Utilities
Requires-Python: >=3.8
License-File: LICENSE
Requires-Dist: abnf~=2.2.0
Requires-Dist: chardet>=5.0.0
Requires-Dist: cint>=1.0.0
Requires-Dist: fickling>=0.0.8
Requires-Dist: graphviz>=0.20.1
Requires-Dist: intervaltree>=2.4.0
Requires-Dist: jinja2>=2.1.0
Requires-Dist: kaitaistruct~=0.10
Requires-Dist: networkx>=2.6.3
Requires-Dist: Pillow>=5.0.0
Requires-Dist: pyreadline3; platform_system == "Windows"
Requires-Dist: pyyaml>=3.13
Requires-Dist: setuptools>=80.9.0
Requires-Dist: pdfminer.six>=20251230
Provides-Extra: demangle
Requires-Dist: cxxfilt; extra == "demangle"
Provides-Extra: dev
Requires-Dist: mypy; extra == "dev"
Requires-Dist: pytest; extra == "dev"
Requires-Dist: flake8; extra == "dev"
Dynamic: author
Dynamic: classifier
Dynamic: description
Dynamic: description-content-type
Dynamic: home-page
Dynamic: license-file
Dynamic: provides-extra
Dynamic: requires-dist
Dynamic: requires-python
Dynamic: summary
